[
{
"id": "1978-1",
"title": "Space Invaders",
"series": "Space Invaders",
"seriesIndex": 1,
"console": "Atari 2600",
"releaseYear": 1978,
"orderIndex": 6.944,
"image": "https://images.launchbox-app.com//0fd94795-e074-402a-a14a-f508db714db1.png"
},



{
"id": "1979-1",
"title": "Asteroids",
"series": "Asteroids",
"seriesIndex": 1,
"console": "Atari 2600",
"releaseYear": 1979,
"orderIndex": 10.011,
"image": "https://images.launchbox-app.com//d51d33af-fda3-4455-8932-c718c152415c.png"
},



{
"id": "1980-1",
"title": "Adventure",
"series": null,
"seriesIndex": null,
"console": "Atari 2600",
"releaseYear": 1980,
"orderIndex": 17.512
},
{
"id": "1980-2",
"title": "Missile Command",
"series": "Missile Command",
"seriesIndex": 1,
"console": "Atari 2600",
"releaseYear": 1980,
"orderIndex": 12.763
},
{
"id": "1980-3",
"title": "Pac-Man",
"series": "Pac-Man",
"seriesIndex": 1,
"console": "Atari 2600",
"releaseYear": 1980,
"orderIndex": 9.617
},



{
"id": "1981-1",
"title": "Centipede",
"series": "Centipede",
"seriesIndex": 1,
"console": "Atari 2600",
"releaseYear": 1981,
"orderIndex": 16.680
},
{
"id": "1981-2",
"title": "Defender",
"series": "Defender",
"seriesIndex": 1,
"console": "Atari 2600",
"releaseYear": 1981,
"orderIndex": 9.251
},
{
"id": "1981-3",
"title": "Frogger",
"series": "Frogger",
"seriesIndex": 1,
"console": "Atari 2600",
"releaseYear": 1981,
"orderIndex": 7.399
},



{
"id": "1982-1",
"title": "River Raid",
"series": null,
"seriesIndex": null,
"console": "Atari 2600",
"releaseYear": 1982,
"orderIndex": 15.774
},
{
"id": "1982-2",
"title": "Moon Patrol",
"series": null,
"seriesIndex": null,
"console": "Atari 2600",
"releaseYear": 1982,
"orderIndex": 13.276
},
{
"id": "1982-3",
"title": "Yars' Revenge",
"series": "Yars",
"seriesIndex": 1,
"console": "Atari 2600",
"releaseYear": 1982,
"orderIndex": 12.857
},
{
"id": "1982-4",
"title": "BurgerTime",
"series": null,
"seriesIndex": null,
"console": "Atari 2600",
"releaseYear": 1982,
"orderIndex": 12.143
},
{
"id": "1982-5",
"title": "Pitfall!",
"series": "Pitfall",
"seriesIndex": 1,
"console": "Atari 2600",
"releaseYear": 1982,
"orderIndex": 8.134
},
{
"id": "1982-6",
"title": "Ms. Pac-Man",
"series": "Pac-Man",
"seriesIndex": 2,
"console": "Atari 2600",
"releaseYear": 1982,
"orderIndex": 4.691
},



{
"id": "1983-1",
"title": "Robot Tank",
"series": null,
"seriesIndex": null,
"console": "Atari 2600",
"releaseYear": 1983,
"orderIndex": 24.593
},
{
"id": "1983-2",
"title": "Keystone Kapers",
"series": null,
"seriesIndex": null,
"console": "Atari 2600",
"releaseYear": 1983,
"orderIndex": 21.170
},
{
"id": "1983-3",
"title": "Decathlon",
"series": null,
"seriesIndex": null,
"console": "Atari 2600",
"releaseYear": 1983,
"orderIndex": 18.935
},
{
"id": "1983-4",
"title": "Star Wars: The Arcade Game",
"series": null,
"seriesIndex": null,
"console": "Atari 2600",
"releaseYear": 1983,
"orderIndex": 4.200
},



{
"id": "1984-1",
"title": "Pitfall II: Lost Caverns",
"series": "Pitfall",
"seriesIndex": 2,
"console": "Atari 2600",
"releaseYear": 1984,
"orderIndex": 6.196
}



,
{
"id": "1985-1",
"title": "Winter Games",
"series": null,
"seriesIndex": null,
"console": "Atari 2600",
"releaseYear": 1985,
"orderIndex": 18.075
}



]


















